flowstream/__init__.py
flowstream/app.py
flowstream/decorators.py
flowstream/sse.py
flowstream-0.1.0.dist-info/METADATA
flowstream-0.1.0.dist-info/WHEEL
flowstream-0.1.0.dist-info/licenses/LICENSE
flowstream-0.1.0.dist-info/RECORD
